cc_bootstrap/__init__.py
cc_bootstrap/config.py
cc_bootstrap/file_system_utils.py
cc_bootstrap/llm_interface.py
cc_bootstrap/main.py
cc_bootstrap/smithery_client.py
cc_bootstrap/analyzers/__init__.py
cc_bootstrap/analyzers/context_builder.py
cc_bootstrap/analyzers/directory_analyzer.py
cc_bootstrap/analyzers/file_sampler.py
cc_bootstrap/cli/__init__.py
cc_bootstrap/cli/app.py
cc_bootstrap/cli/formatters.py
cc_bootstrap/cli/interactive.py
cc_bootstrap/cli/progress.py
cc_bootstrap/dynamic/__init__.py
cc_bootstrap/dynamic/command_generator.py
cc_bootstrap/dynamic/config_generator.py
cc_bootstrap/dynamic/doc_generator.py
cc_bootstrap/dynamic/workflow.py
cc_bootstrap/providers/__init__.py
cc_bootstrap/providers/anthropic_provider.py
cc_bootstrap/providers/base_provider.py
cc_bootstrap/providers/bedrock_provider.py
cc_bootstrap/providers/provider_factory.py
cc_bootstrap/research/__init__.py
cc_bootstrap/research/perplexity_client.py
cc_bootstrap/research/question_generator.py
cc_bootstrap/templates/__init__.py
cc_bootstrap/templates/defaults/settings.json
cc_bootstrap/templates/prompts/action_plan_single.j2
cc_bootstrap/templates/prompts/action_plan_squad.j2
cc_bootstrap/templates/prompts/all_custom_commands.j2
cc_bootstrap/templates/prompts/claude_md.j2
cc_bootstrap/templates/prompts/generate_research_questions.j2
cc_bootstrap/templates/prompts/mcp_config.j2
cc_bootstrap-0.2.2.dist-info/METADATA
cc_bootstrap-0.2.2.dist-info/WHEEL
cc_bootstrap-0.2.2.dist-info/entry_points.txt
cc_bootstrap-0.2.2.dist-info/licenses/LICENSE
cc_bootstrap-0.2.2.dist-info/RECORD
