Metadata-Version: 2.4
Name: cc-bootstrap
Version: 0.2.2
Summary: A Python CLI tool that automates the setup of Claude Code configuration files
Project-URL: Homepage, https://github.com/vinodismyname/ClaudeCodeBootstrap
Project-URL: Bug Tracker, https://github.com/vinodismyname/ClaudeCodeBootstrap/issues
Author-email: Vinod <vinodismyname@msn.com>
License: MIT
License-File: LICENSE
Classifier: License :: OSI Approved :: MIT License
Classifier: Operating System :: OS Independent
Classifier: Programming Language :: Python :: 3
Requires-Python: >=3.12
Requires-Dist: anthropic>=0.51.0
Requires-Dist: boto3>=1.28.0
Requires-Dist: jinja2>=3.1.6
Requires-Dist: python-dotenv>=1.0.0
Requires-Dist: pyyaml>=6.0
Requires-Dist: requests>=2.32.3
Requires-Dist: rich>=13.0.0
Requires-Dist: typer>=0.9.0
Provides-Extra: dev
Requires-Dist: black>=23.0.0; extra == 'dev'
Requires-Dist: flake8>=6.0.0; extra == 'dev'
Requires-Dist: isort>=5.0.0; extra == 'dev'
Requires-Dist: mypy>=1.0.0; extra == 'dev'
Requires-Dist: pytest-cov>=4.0.0; extra == 'dev'
Requires-Dist: pytest>=7.0.0; extra == 'dev'
